IQDMPDF/__init__.py
IQDMPDF/_version.py
IQDMPDF/file_processor.py
IQDMPDF/main.py
IQDMPDF/paths.py
IQDMPDF/pdf_reader.py
IQDMPDF/utilities.py
IQDMPDF/parsers/__init__.py
IQDMPDF/parsers/delta4.py
IQDMPDF/parsers/generic.py
IQDMPDF/parsers/parser.py
IQDMPDF/parsers/sncpatient.py
IQDMPDF/parsers/verisoft.py
IQDMPDF/report_templates/sncpatient.json
IQDMPDF/report_templates/sncpatient2020.json
tests/.DS_Store
tests/__init__.py
tests/test_file_processor.py
tests/test_pdf_reader.py
tests/test_report_parsers.py
tests/test_utilities.py
tests/__pycache__/__init__.cpython-37.pyc
tests/__pycache__/test_file_processor.cpython-37-pytest-6.2.2.pyc
tests/__pycache__/test_file_processor.cpython-37.pyc
tests/__pycache__/test_pdf_reader.cpython-37-pytest-6.2.2.pyc
tests/__pycache__/test_pdf_reader.cpython-37.pyc
tests/__pycache__/test_report_parsers.cpython-37-pytest-6.2.2.pyc
tests/__pycache__/test_report_parsers.cpython-37.pyc
tests/__pycache__/test_utilities.cpython-37-pytest-6.2.2.pyc
tests/__pycache__/test_utilities.cpython-37.pyc
tests/test_data/.DS_Store
tests/test_data/expected_report_data.py
tests/test_data/simple_test.pdf
tests/test_data/__pycache__/expected_report_data.cpython-37.pyc
tests/test_data/example_reports/.DS_Store
tests/test_data/example_reports/delta4/.DS_Store
tests/test_data/example_reports/delta4/UChicago/DCAM_example_1.pdf
tests/test_data/example_reports/delta4/UChicago/DCAM_example_2.pdf
tests/test_data/example_reports/delta4/UChicago/DCAM_example_3.pdf
tests/test_data/example_reports/delta4/UChicago/DCAM_example_4.pdf
tests/test_data/example_reports/delta4/UChicago/DCAM_example_5.pdf
tests/test_data/example_reports/delta4/UChicago/DCAM_example_6.pdf
tests/test_data/example_reports/delta4/UChicago/DCAM_example_7.pdf
tests/test_data/example_reports/delta4/UChicago/DCAM_example_8.pdf
tests/test_data/example_reports/delta4/UChicago/DCAM_example_9.pdf
tests/test_data/example_reports/delta4/UChicago/SCH_example_1.pdf
IQDMPDF-0.3.0.dist-info/LICENSE
IQDMPDF-0.3.0.dist-info/METADATA
IQDMPDF-0.3.0.dist-info/WHEEL
IQDMPDF-0.3.0.dist-info/entry_points.txt
IQDMPDF-0.3.0.dist-info/top_level.txt
IQDMPDF-0.3.0.dist-info/RECORD
