Metadata-Version: 2.1
Name: IQDMPDF
Version: 0.3.0
Summary: Scans a directory for IMRT QA results
Home-page: https://github.com/IQDM/IQDM-PDF
Author: Dan Cutright
Maintainer: Dan Cutright
License: MIT License
Download-URL: https://github.com/IQDM/IQDM-PDF.git
Keywords: data mining,radiation oncology,IMRT QA
Platform: UNKNOWN
Classifier: License :: OSI Approved :: MIT License
Classifier: Intended Audience :: End Users/Desktop
Classifier: Intended Audience :: Healthcare Industry
Classifier: Intended Audience :: Science/Research
Classifier: Natural Language :: English
Classifier: Development Status :: 2 - Pre-Alpha
Classifier: Programming Language :: Python
Classifier: Programming Language :: Python :: 3.6
Classifier: Programming Language :: Python :: 3.7
Classifier: Programming Language :: Python :: 3.8
Classifier: Programming Language :: Python :: 3.9
Classifier: Operating System :: OS Independent
Classifier: Topic :: Scientific/Engineering :: Medical Science Apps.
Classifier: Topic :: Scientific/Engineering :: Physics
Requires-Python: >3.5
Requires-Dist: pdfminer.six
Requires-Dist: tqdm
